splitit_async/__init__.py
splitit_async/api_client.py
splitit_async/configuration.py
splitit_async/rest.py
splitit_async/api/__init__.py
splitit_async/api/create_installment_plan_api.py
splitit_async/api/info_api.py
splitit_async/api/infrastructure_api.py
splitit_async/api/installment_plan_api.py
splitit_async/api/login_api.py
splitit_async/models/__init__.py
splitit_async/models/address_data.py
splitit_async/models/address_data2.py
splitit_async/models/amount_details.py
splitit_async/models/amount_details2.py
splitit_async/models/approve_installment_plan_request.py
splitit_async/models/authentication_type.py
splitit_async/models/cancel_installment_plan_request.py
splitit_async/models/card_brand.py
splitit_async/models/card_data.py
splitit_async/models/card_result.py
splitit_async/models/card_type.py
splitit_async/models/cart_data.py
splitit_async/models/chargeback_request.py
splitit_async/models/consumer_data.py
splitit_async/models/create_installment_plan_legacy_response.py
splitit_async/models/create_installment_plan_request.py
splitit_async/models/create_installments_plan_response.py
splitit_async/models/currency.py
splitit_async/models/delay_resolution.py
splitit_async/models/dispute_status.py
splitit_async/models/disputes.py
splitit_async/models/error.py
splitit_async/models/events_endpoints.py
splitit_async/models/extended_currency.py
splitit_async/models/external_auth.py
splitit_async/models/fraud_check.py
splitit_async/models/fraud_check_result.py
splitit_async/models/get3_d_secure_parameters_request.py
splitit_async/models/get3_d_secure_parameters_response.py
splitit_async/models/get_fraud_status_display_request.py
splitit_async/models/get_fraud_status_display_response.py
splitit_async/models/get_initiated_installment_plan_request.py
splitit_async/models/get_initiated_installment_plan_response.py
splitit_async/models/get_initiated_update_payment_data_response.py
splitit_async/models/get_installment_schedules_request.py
splitit_async_async-1.6.10.dist-info/METADATA
splitit_async_async-1.6.10.dist-info/WHEEL
splitit_async_async-1.6.10.dist-info/top_level.txt
splitit_async_async-1.6.10.dist-info/RECORD
